<?xml version="1.0" encoding="utf-8"?>
<!DOCTYPE population SYSTEM "../dtd/population_v6.dtd">

<population>



<!-- ====================================================================== -->

	<person id="1">
		<plan selected="yes">
			<activity type="h" link="341987464_1" end_time="01:12:29" >
			</activity>
			<leg mode="car">
			</leg>
			<activity type="w" link="261801022_0_r" end_time="05:33:59" >
			</activity>
			<leg mode="car">
			</leg>
			<activity type="h" link="341987464_1" >
			</activity>
		</plan>

	</person>

<!-- ====================================================================== -->

	<person id="10">
		<plan selected="yes">
			<activity type="h" link="233476167_1_r" end_time="03:13:28" >
			</activity>
			<leg mode="car">
			</leg>
			<activity type="w" link="587053234_0" end_time="05:55:47" >
			</activity>
			<leg mode="car">
			</leg>
			<activity type="h" link="233476167_1_r" >
			</activity>
		</plan>

	</person>

<!-- ====================================================================== -->

	<person id="100">
		<plan selected="yes">
			<activity type="h" link="627247534_0" end_time="11:13:05" >
			</activity>
			<leg mode="car">
			</leg>
			<activity type="w" link="223803788_0" end_time="13:13:07" >
			</activity>
			<leg mode="car">
			</leg>
			<activity type="h" link="627247534_0" >
			</activity>
		</plan>

	</person>

<!-- ====================================================================== -->

	<person id="101">
		<plan selected="yes">
			<activity type="h" link="694429902_0" end_time="11:36:42" >
			</activity>
			<leg mode="car">
			</leg>
			<activity type="w" link="579357189_0" end_time="16:41:53" >
			</activity>
			<leg mode="car">
			</leg>
			<activity type="h" link="694429902_0" >
			</activity>
		</plan>

	</person>

<!-- ====================================================================== -->

	<person id="102">
		<plan selected="yes">
			<activity type="h" link="317351530_2" end_time="11:12:18" >
			</activity>
			<leg mode="car">
			</leg>
			<activity type="w" link="598686079_0" end_time="15:40:04" >
			</activity>
			<leg mode="car">
			</leg>
			<activity type="h" link="317351530_2" >
			</activity>
		</plan>

	</person>

<!-- ====================================================================== -->

	<person id="103">
		<plan selected="yes">
			<activity type="h" link="358572804_1" end_time="12:38:27" >
			</activity>
			<leg mode="car">
			</leg>
			<activity type="w" link="353899403_0_r" end_time="20:06:37" >
			</activity>
			<leg mode="car">
			</leg>
			<activity type="h" link="358572804_1" >
			</activity>
		</plan>

	</person>

<!-- ====================================================================== -->

	<person id="104">
		<plan selected="yes">
			<activity type="h" link="42242812_6" end_time="12:31:34" >
			</activity>
			<leg mode="car">
			</leg>
			<activity type="w" link="358588774_0" end_time="17:35:14" >
			</activity>
			<leg mode="car">
			</leg>
			<activity type="h" link="42242812_6" >
			</activity>
		</plan>

	</person>

<!-- ====================================================================== -->

	<person id="105">
		<plan selected="yes">
			<activity type="h" link="132231472_0" end_time="12:54:17" >
			</activity>
			<leg mode="car">
			</leg>
			<activity type="w" link="279012468_3_r" end_time="20:52:23" >
			</activity>
			<leg mode="car">
			</leg>
			<activity type="h" link="132231472_0" >
			</activity>
		</plan>

	</person>

<!-- ====================================================================== -->

	<person id="106">
		<plan selected="yes">
			<activity type="h" link="300208860_13" end_time="12:00:19" >
			</activity>
			<leg mode="car">
			</leg>
			<activity type="w" link="506596052_0_r" end_time="18:38:25" >
			</activity>
			<leg mode="car">
			</leg>
			<activity type="h" link="300208860_13" >
			</activity>
		</plan>

	</person>

<!-- ====================================================================== -->

	<person id="107">
		<plan selected="yes">
			<activity type="h" link="324162139_0_r" end_time="12:19:45" >
			</activity>
			<leg mode="car">
			</leg>
			<activity type="w" link="600936621_3" end_time="19:39:49" >
			</activity>
			<leg mode="car">
			</leg>
			<activity type="h" link="324162139_0_r" >
			</activity>
		</plan>

	</person>

<!-- ====================================================================== -->

	<person id="108">
		<plan selected="yes">
			<activity type="h" link="16983310_8" end_time="12:31:06" >
			</activity>
			<leg mode="car">
			</leg>
			<activity type="w" link="627186645_0" end_time="19:04:39" >
			</activity>
			<leg mode="car">
			</leg>
			<activity type="h" link="16983310_8" >
			</activity>
		</plan>

	</person>

<!-- ====================================================================== -->

	<person id="109">
		<plan selected="yes">
			<activity type="h" link="579434342_2" end_time="12:10:01" >
			</activity>
			<leg mode="car">
			</leg>
			<activity type="w" link="16985131_8_r" end_time="18:59:05" >
			</activity>
			<leg mode="car">
			</leg>
			<activity type="h" link="579434342_2" >
			</activity>
		</plan>

	</person>

<!-- ====================================================================== -->

	<person id="11">
		<plan selected="yes">
			<activity type="h" link="16986947_4" end_time="03:26:11" >
			</activity>
			<leg mode="car">
			</leg>
			<activity type="w" link="16982302_11_r" end_time="03:57:26" >
			</activity>
			<leg mode="car">
			</leg>
			<activity type="h" link="16986947_4" >
			</activity>
		</plan>

	</person>

<!-- ====================================================================== -->

	<person id="110">
		<plan selected="yes">
			<activity type="h" link="279465840_0_r" end_time="12:10:25" >
			</activity>
			<leg mode="car">
			</leg>
			<activity type="w" link="583463072_0" end_time="13:00:14" >
			</activity>
			<leg mode="car">
			</leg>
			<activity type="h" link="279465840_0_r" >
			</activity>
		</plan>

	</person>

<!-- ====================================================================== -->

	<person id="111">
		<plan selected="yes">
			<activity type="h" link="314217204_0_r" end_time="12:26:00" >
			</activity>
			<leg mode="car">
			</leg>
			<activity type="w" link="1138836699_0_r" end_time="17:16:31" >
			</activity>
			<leg mode="car">
			</leg>
			<activity type="h" link="314217204_0_r" >
			</activity>
		</plan>

	</person>

<!-- ====================================================================== -->

	<person id="112">
		<plan selected="yes">
			<activity type="h" link="972598160_3" end_time="12:46:04" >
			</activity>
			<leg mode="car">
			</leg>
			<activity type="w" link="279059781_0" end_time="17:43:35" >
			</activity>
			<leg mode="car">
			</leg>
			<activity type="h" link="972598160_3" >
			</activity>
		</plan>

	</person>
	
<!-- ====================================================================== -->

</population>
